{"api_dimensions.md":"DbhzBY1D","api_lookuparrays.md":"Dtj9MwpD","api_reference.md":"B6QSg_Og","basics.md":"BRAyWN_e","broadcast_dims.md":"BspaQRx1","cuda.md":"CFpWIRSG","dimarrays.md":"CD8Efzo1","dimensions.md":"CI-NXDzb","diskarrays.md":"4aGmOwDi","extending_dd.md":"Duz-MW62","get_info.md":"Dv0WFCf2","groupby.md":"BAnwYmjf","index.md":"Dn5nC5S-","integrations.md":"DMDtkH-s","object_modification.md":"D6vxdwM5","plots.md":"BYJD1d_y","selectors.md":"D-dbwVv0","stacks.md":"BxDCVBSX","tables.md":"sW99tgnb"}
